rm_sec_toolkit-0.2.4.data/scripts/rm-sec-toolkit
rmsectkf/__init__.py
rmsectkf/core/__init__.py
rmsectkf/core/commands/__init__.py
rmsectkf/core/commands/add_command.py
rmsectkf/core/commands/base_command.py
rmsectkf/core/commands/create_command.py
rmsectkf/core/commands/flag_command.py
rmsectkf/core/commands/module_command.py
rmsectkf/core/commands/note_command.py
rmsectkf/core/helpers/__init__.py
rmsectkf/core/helpers/menu_helper.py
rmsectkf/core/helpers/print_helper.py
rmsectkf/core/helpers/update_helper.py
rmsectkf/core/mappers/__init__.py
rmsectkf/core/mappers/port_mapper.py
rmsectkf/core/module/__init__.py
rmsectkf/core/module/module_loader.py
rmsectkf/core/module/rm_category.py
rmsectkf/core/module/rm_module.py
rmsectkf/core/modules/__init__.py
rmsectkf/core/modules/base_module.py
rmsectkf/core/modules/local/__init__.py
rmsectkf/core/modules/local/local_module.py
rmsectkf/core/modules/others/__init__.py
rmsectkf/core/modules/others/others_module.py
rmsectkf/core/modules/others/add/__init__.py
rmsectkf/core/modules/others/add/add_module.py
rmsectkf/core/modules/others/create/__init__.py
rmsectkf/core/modules/others/create/create_module.py
rmsectkf/core/modules/remote/__init__.py
rmsectkf/core/modules/remote/remote_module.py
rmsectkf/core/modules/remote/exploit/__init__.py
rmsectkf/core/modules/remote/exploit/exploit_module.py
rmsectkf/core/modules/remote/exploit/web/__init__.py
rmsectkf/core/modules/remote/exploit/web/web_module.py
rmsectkf/core/modules/remote/gathering/__init__.py
rmsectkf/core/modules/remote/gathering/gathering_module.py
rmsectkf/core/modules/remote/gathering/scanner/__init__.py
rmsectkf/core/modules/remote/gathering/scanner/scanner_module.py
rmsectkf/core/network/__init__.py
rmsectkf/core/network/port.py
rmsectkf/core/network/port_service_map.py
rmsectkf/core/network/raw_ip.py
rmsectkf/core/project/__init__.py
rmsectkf/core/project/rm_project.py
rm_sec_toolkit-0.2.4.dist-info/LICENSE
rm_sec_toolkit-0.2.4.dist-info/METADATA
rm_sec_toolkit-0.2.4.dist-info/WHEEL
rm_sec_toolkit-0.2.4.dist-info/entry_points.txt
rm_sec_toolkit-0.2.4.dist-info/top_level.txt
rm_sec_toolkit-0.2.4.dist-info/RECORD
